nwm_explorer/__init__.py
nwm_explorer/_version.py
nwm_explorer/data/__init__.py
nwm_explorer/data/download.py
nwm_explorer/data/mapping.py
nwm_explorer/data/nwm.py
nwm_explorer/data/routelink.py
nwm_explorer/data/usgs.py
nwm_explorer/data/usgs_site_info.py
nwm_explorer/evaluation/__init__.py
nwm_explorer/evaluation/compute.py
nwm_explorer/evaluation/metrics.py
nwm_explorer/evaluation/pairs.py
nwm_explorer/interfaces/__init__.py
nwm_explorer/interfaces/cli.py
nwm_explorer/interfaces/configuration.py
nwm_explorer/interfaces/filters.py
nwm_explorer/interfaces/gui.py
nwm_explorer/interfaces/site_information.py
nwm_explorer/logging/__init__.py
nwm_explorer/logging/logger.py
nwm_explorer/plots/__init__.py
nwm_explorer/plots/barplot.py
nwm_explorer/plots/histogram.py
nwm_explorer/plots/hydrograph.py
nwm_explorer/plots/site_map.py
nwm_explorer/tables/status.py
nwm_explorer-0.5.0.dist-info/licenses/LICENSE
nwm_explorer-0.5.0.dist-info/METADATA
nwm_explorer-0.5.0.dist-info/WHEEL
nwm_explorer-0.5.0.dist-info/entry_points.txt
nwm_explorer-0.5.0.dist-info/top_level.txt
nwm_explorer-0.5.0.dist-info/RECORD
