Metadata-Version: 2.4
Name: nwm_explorer
Version: 0.5.0
Summary: A web-based application used to explore National Water Model output and evaluation metrics.
Author-email: "Jason A. Regina" <jregina@duck.com>
License-Expression: Apache-2.0
Project-URL: Homepage, https://github.com/jarq6c/nwm-explorer
Project-URL: Documentation, https://jarq6c.github.io/nwm-explorer
Project-URL: Repository, https://github.com/jarq6c/nwm-explorer
Project-URL: Bug Tracker, https://github.com/jarq6c/nwm-explorer/issues
Classifier: Development Status :: 3 - Alpha
Classifier: Intended Audience :: Education
Classifier: Intended Audience :: Science/Research
Classifier: Programming Language :: Python :: 3.10
Classifier: Programming Language :: Python :: 3.11
Classifier: Programming Language :: Python :: 3.12
Classifier: Topic :: Scientific/Engineering :: Hydrology
Classifier: Operating System :: OS Independent
Requires-Python: >=3.10
License-File: LICENSE
Requires-Dist: click
Requires-Dist: pandas
Requires-Dist: polars
Requires-Dist: xarray
Requires-Dist: aiohttp
Requires-Dist: aiofiles
Requires-Dist: numba
Requires-Dist: pyarrow
Requires-Dist: netcdf4
Requires-Dist: dask
Requires-Dist: panel
Requires-Dist: geopandas
Requires-Dist: plotly
Requires-Dist: colorcet
Requires-Dist: arch
Requires-Dist: us
Requires-Dist: hydrotools.nwis_client
Provides-Extra: develop
Requires-Dist: pytest; extra == "develop"
Dynamic: license-file
